README.md
setup.cfg
setup.py
towise/Towise.py
towise/__init__.py
towise.egg-info/PKG-INFO
towise.egg-info/SOURCES.txt
towise.egg-info/dependency_links.txt
towise.egg-info/requires.txt
towise.egg-info/top_level.txt