Metadata-Version: 1.1
Name: towise
Version: 0.1.7
Summary: Towise assists you to detect human faces and bodies with using the latest and reliable technology.
Home-page: https://github.com/argedor/TowisePythonAPI.git
Author: Harun KELEŞOĞLU
Author-email: harunkelesoglu_@hotmail.com
License: MIT
Download-URL: https://github.com/argedor/TowisePythonAPI/archive/1.7.tar.gz
Keywords: towise,face detection,body detection,emotion detection,face comparing
Platform: UNKNOWN
Classifier: Programming Language :: Python :: 3.6
Classifier: License :: OSI Approved :: MIT License
Classifier: Operating System :: OS Independent
